{"cameraMode":{"drawMode":0,"name":"Shaded","section":"Shading Mode"},"sceneLighting":true,"audioPlay":false,"sceneViewState":{"m_AlwaysRefresh":false,"showFog":true,"showSkybox":true,"showFlares":true,"showImageEffects":true,"showParticleSystems":true,"showVisualEffectGraphs":true,"m_FxEnabled":false},"in2DMode":false,"pivot":{"x":7.240686416625977,"y":1.3462435007095338,"z":4.262093544006348},"rotation":{"x":-0.060428302735090259,"y":-0.6800102591514587,"z":0.05649270862340927,"w":-0.7286099195480347},"size":4.934013366699219,"orthographic":false}